rscmw_base/__init__.py
rscmw_base/enums.py
rscmw_base/py.typed.py
rscmw_base/repcap.py
rscmw_base/rscmw_base.py
rscmw_base/CustomFiles/__init__.py
rscmw_base/CustomFiles/events.py
rscmw_base/CustomFiles/reliability.py
rscmw_base/CustomFiles/utilities.py
rscmw_base/Implementations/ContinuePy.py
rscmw_base/Implementations/FirmwareUpdate.py
rscmw_base/Implementations/Get.py
rscmw_base/Implementations/GlobalClearStatus.py
rscmw_base/Implementations/GlobalWait.py
rscmw_base/Implementations/GotoLocal.py
rscmw_base/Implementations/MacroCreate.py
rscmw_base/Implementations/Procedure.py
rscmw_base/Implementations/RecallState.py
rscmw_base/Implementations/SaveState.py
rscmw_base/Implementations/TriggerInvoke.py
rscmw_base/Implementations/Unit.py
rscmw_base/Implementations/__init__.py
rscmw_base/Implementations/Buffer/LineCount.py
rscmw_base/Implementations/Buffer/__init__.py
rscmw_base/Implementations/Calibration/Ipc.py
rscmw_base/Implementations/Calibration/Ipcr.py
rscmw_base/Implementations/Calibration/__init__.py
rscmw_base/Implementations/Calibration/Latest/Specific.py
rscmw_base/Implementations/Calibration/Latest/__init__.py
rscmw_base/Implementations/Catalog/Salignment.py
rscmw_base/Implementations/Catalog/__init__.py
rscmw_base/Implementations/Catalog/Correction/__init__.py
rscmw_base/Implementations/Catalog/Correction/IfEqualizer/__init__.py
rscmw_base/Implementations/Catalog/Correction/IfEqualizer/Slot/RxFilter.py
rscmw_base/Implementations/Catalog/Correction/IfEqualizer/Slot/TxFilter.py
rscmw_base/Implementations/Catalog/Correction/IfEqualizer/Slot/__init__.py
rscmw_base/Implementations/Cmwd/State.py
rscmw_base/Implementations/Cmwd/__init__.py
rscmw_base/Implementations/Configure/Cmwd.py
rscmw_base/Implementations/Configure/Ipcr.py
rscmw_base/Implementations/Configure/Salignment.py
rscmw_base/Implementations/Configure/__init__.py
rscmw_base/Implementations/Configure/Adjustment/SfDefault.py
rscmw_base/Implementations/Configure/Adjustment/__init__.py
rscmw_base-4.0.250.dist-info/METADATA
rscmw_base-4.0.250.dist-info/WHEEL
rscmw_base-4.0.250.dist-info/top_level.txt
rscmw_base-4.0.250.dist-info/RECORD
